DESCRIPTION.md
LICENSE.txt
MANIFEST.in
README.md
setup.cfg
setup.py
src/snowflake/sqlalchemy/__init__.py
src/snowflake/sqlalchemy/_constants.py
src/snowflake/sqlalchemy/base.py
src/snowflake/sqlalchemy/custom_commands.py
src/snowflake/sqlalchemy/custom_types.py
src/snowflake/sqlalchemy/provision.py
src/snowflake/sqlalchemy/requirements.py
src/snowflake/sqlalchemy/snowdialect.py
src/snowflake/sqlalchemy/util.py
src/snowflake/sqlalchemy/version.py
src/snowflake_sqlalchemy_2.egg-info/PKG-INFO
src/snowflake_sqlalchemy_2.egg-info/SOURCES.txt
src/snowflake_sqlalchemy_2.egg-info/dependency_links.txt
src/snowflake_sqlalchemy_2.egg-info/entry_points.txt
src/snowflake_sqlalchemy_2.egg-info/not-zip-safe
src/snowflake_sqlalchemy_2.egg-info/requires.txt
src/snowflake_sqlalchemy_2.egg-info/top_level.txt