Metadata-Version: 2.1
Name: snowflake-sqlalchemy-2
Version: 0.1.6
Summary: Snowflake SQLAlchemy Dialect (including patches for SQLAlchemy 2 support)
Home-page: https://www.snowflake.com/
Author: Edwin Onuonga
Author-email: edwinonuonga@gmail.com
License: Apache-2.0
Project-URL: Documentation, https://docs.snowflake.com/en/user-guide/sqlalchemy.html
Project-URL: Source, https://github.com/snowflakedb/snowflake-sqlalchemy
Project-URL: Issues, https://github.com/snowflakedb/snowflake-sqlalchemy/issues
Project-URL: Changelog, https://github.com/snowflakedb/snowflake-sqlalchemy/blob/main/DESCRIPTION.md
Keywords: Snowflake db database cloud analytics warehouse
Classifier: Development Status :: 5 - Production/Stable
Classifier: Environment :: Console
Classifier: Environment :: Other Environment
Classifier: Intended Audience :: Developers
Classifier: Intended Audience :: Education
Classifier: Intended Audience :: Information Technology
Classifier: Intended Audience :: System Administrators
Classifier: License :: OSI Approved :: Apache Software License
Classifier: Operating System :: OS Independent
Classifier: Programming Language :: Python :: 3
Classifier: Programming Language :: Python :: 3 :: Only
Classifier: Programming Language :: Python :: 3.7
Classifier: Programming Language :: Python :: 3.8
Classifier: Programming Language :: Python :: 3.9
Classifier: Programming Language :: Python :: 3.10
Classifier: Programming Language :: Python :: 3.11
Classifier: Programming Language :: SQL
Classifier: Topic :: Database
Classifier: Topic :: Scientific/Engineering :: Information Analysis
Classifier: Topic :: Software Development
Classifier: Topic :: Software Development :: Libraries
Classifier: Topic :: Software Development :: Libraries :: Application Frameworks
Classifier: Topic :: Software Development :: Libraries :: Python Modules
Requires-Python: >=3.7
License-File: LICENSE.txt
Requires-Dist: importlib-metadata; python_version < "3.8"
Requires-Dist: sqlalchemy>=1.4.0
Requires-Dist: snowflake-connector-python>=3.4.0
Provides-Extra: development
Requires-Dist: pytest; extra == "development"
Requires-Dist: pytest-cov; extra == "development"
Requires-Dist: pytest-rerunfailures; extra == "development"
Requires-Dist: pytest-timeout; extra == "development"
Requires-Dist: mock; extra == "development"
Requires-Dist: pytz; extra == "development"
Requires-Dist: numpy; extra == "development"
Provides-Extra: pandas
Requires-Dist: snowflake-connector-python[pandas]>=3.4.0; extra == "pandas"
